{
  "CWMP_AUTH_USERNAME":"super",
  "CWMP_AUTH_PASSWORD":"super",
  "MONGODB_CONNECTION_URL" : "mongodb://127.0.0.1/genieacs",
  "CWMP_INTERFACE" : "0.0.0.0",
  "CWMP_PORT" : 9102,
  "CWMP_SSL" : false,
  "NBI_INTERFACE" : "0.0.0.0",
  "NBI_PORT" : 9103,
  "FS_INTERFACE" : "0.0.0.0",
  "FS_PORT" : 9104,
  "FS_HOSTNAME" : "acs.example.com",
  "DEBUG" : false,
  "CWMP_LOG_FILE" : "log/cwmp.log",
  "CWMP_ACCESS_LOG_FILE" : "log/access.log",
  "FS_LOG_FILE" : "log/fs.log",
  "FS_ACCESS_LOG_FILE" : "log/fsaccess.log",
  "COOKIES_PATH" : "sessions/",
  "NBI_LOG_FILE" : "log/nbi.log",
  "NBI_ACCESS_LOG_FILE" : "log/nbiaccess.log"
}
